mcpd_plugins/__init__.py
mcpd_plugins/_version.py
mcpd_plugins/base_plugin.py
mcpd_plugins/exceptions.py
mcpd_plugins/py.typed
mcpd_plugins/server.py
mcpd_plugins/v1/__init__.py
mcpd_plugins/v1/plugins/__init__.py
mcpd_plugins/v1/plugins/plugin_pb2.py
mcpd_plugins/v1/plugins/plugin_pb2_grpc.py
mcpd_plugins-0.0.1.dist-info/licenses/LICENSE
mcpd_plugins-0.0.1.dist-info/METADATA
mcpd_plugins-0.0.1.dist-info/WHEEL
mcpd_plugins-0.0.1.dist-info/top_level.txt
mcpd_plugins-0.0.1.dist-info/RECORD
