Metadata-Version: 2.4
Name: mcpd-plugins
Version: 0.0.1
Summary: mcpd plugins Python SDK
License: Apache-2.0
Requires-Python: >=3.11
License-File: LICENSE
Requires-Dist: grpcio>=1.76.0
Requires-Dist: protobuf<7,>=6.33.0
Dynamic: license-file
